hopfieldnetwork/__about__.py
hopfieldnetwork/__init__.py
hopfieldnetwork/gui.py
hopfieldnetwork/libary.py
hopfieldnetwork/tk_utils.py
hopfieldnetwork/utils.py
hopfieldnetwork/data/famous_physicists/curie.jpg
hopfieldnetwork/data/famous_physicists/de_broglie.jpg
hopfieldnetwork/data/famous_physicists/dirac.jpg
hopfieldnetwork/data/famous_physicists/einstein.jpg
hopfieldnetwork/data/famous_physicists/feynman.jpg
hopfieldnetwork/data/famous_physicists/heisenberg.jpg
hopfieldnetwork/data/famous_physicists/hilbert.jpg
hopfieldnetwork/data/famous_physicists/humboldt.jpg
hopfieldnetwork/data/famous_physicists/newton.jpg
hopfieldnetwork/data/famous_physicists/schroedinger.jpg
hopfieldnetwork/data/hopfield_network_examples/abc_25neu_3pat.npz
hopfieldnetwork/data/hopfield_network_examples/oscillating_when_syn_update_9neu_5pat.npz
hopfieldnetwork/data/icon/icon.gif
hopfieldnetwork/data/icon/icon.svg
hopfieldnetwork-1.0.1.dist-info/LICENSE
hopfieldnetwork-1.0.1.dist-info/METADATA
hopfieldnetwork-1.0.1.dist-info/WHEEL
hopfieldnetwork-1.0.1.dist-info/entry_points.txt
hopfieldnetwork-1.0.1.dist-info/top_level.txt
hopfieldnetwork-1.0.1.dist-info/RECORD
