Metadata-Version: 2.1
Name: hopfieldnetwork
Version: 1.0.1
Summary: A Python implementation of the Hopfield network
Home-page: https://github.com/andreasfelix/hopfieldnetwork
Author: Felix Andreas
License: GNU General Public License v3.0
Platform: UNKNOWN
Classifier: Development Status :: 5 - Production/Stable
Classifier: Intended Audience :: Science/Research
Classifier: License :: OSI Approved :: GNU General Public License v3 (GPLv3)
Classifier: Programming Language :: Python
Classifier: Topic :: Scientific/Engineering
Requires-Python: >=2.7
Requires-Dist: numpy
Requires-Dist: matplotlib
Requires-Dist: pillow
